LICENSE
controlled_vocabulary/__init__.py
controlled_vocabulary/admin.py
controlled_vocabulary/apps.py
controlled_vocabulary/defaults.py
controlled_vocabulary/management/__init__.py
controlled_vocabulary/management/commands/__init__.py
controlled_vocabulary/management/commands/vocab.py
controlled_vocabulary/migrations/0001_initial.py
controlled_vocabulary/migrations/0002_auto_20191207_0103.py
controlled_vocabulary/migrations/0003_auto_20191211_0113.py
controlled_vocabulary/migrations/0004_remove_controlledvocabulary_test.py
controlled_vocabulary/migrations/__init__.py
controlled_vocabulary/models.py
controlled_vocabulary/settings.py
controlled_vocabulary/static/admin/css/controlled_term_widget.css
controlled_vocabulary/static/admin/js/controlled_term_widget.js
controlled_vocabulary/templates/controlled_vocabulary/controlled_term.html
controlled_vocabulary/tests.py
controlled_vocabulary/urls.py
controlled_vocabulary/utils.py
controlled_vocabulary/views.py
controlled_vocabulary/vocabularies/__init__.py
controlled_vocabulary/vocabularies/base.py
controlled_vocabulary/vocabularies/base_csv.py
controlled_vocabulary/vocabularies/base_http.py
controlled_vocabulary/vocabularies/base_list.py
controlled_vocabulary/vocabularies/dcmitype.py
controlled_vocabulary/vocabularies/fast_forms.py
controlled_vocabulary/vocabularies/fast_topic.py
controlled_vocabulary/vocabularies/iso15924.py
controlled_vocabulary/vocabularies/iso639_2.py
controlled_vocabulary/vocabularies/mime.py
controlled_vocabulary/vocabularies/schema.py
controlled_vocabulary/vocabularies/viaf.py
controlled_vocabulary/vocabularies/wikidata.py
django_controlled_vocabulary-0.12.dist-info/LICENSE
django_controlled_vocabulary-0.12.dist-info/WHEEL
django_controlled_vocabulary-0.12.dist-info/METADATA
django_controlled_vocabulary-0.12.dist-info/RECORD
