Metadata-Version: 2.1
Name: django-controlled-vocabulary
Version: 0.12
Summary: Link your data to authority lists or your own controlled lists
Home-page: https://github.com/kingsdigitallab/django-controlled-vocabulary
License: MIT
Keywords: controlled-vocabulary,linked-data,vocabulary,metadata
Author: geoffroy-noel-ddh
Author-email: geoffroy.noel@kcl.ac.uk
Requires-Python: >=3.5,<4.0
Classifier: Development Status :: 4 - Beta
Classifier: Environment :: Web Environment
Classifier: Framework :: Django :: 2.2
Classifier: Framework :: Django :: 3.0
Classifier: Framework :: Django :: 3.1
Classifier: Framework :: Django :: 3.2
Classifier: License :: OSI Approved :: MIT License
Classifier: Operating System :: OS Independent
Classifier: Programming Language :: Python :: 3
Classifier: Programming Language :: Python :: 3.10
Classifier: Programming Language :: Python :: 3.5
Classifier: Programming Language :: Python :: 3.6
Classifier: Programming Language :: Python :: 3.7
Classifier: Programming Language :: Python :: 3.8
Classifier: Programming Language :: Python :: 3.9
Provides-Extra: toml_tox
Requires-Dist: coverage (>=4.5,<5.0); extra == "toml_tox"
Requires-Dist: django (>=2.2,<3.3)
Requires-Dist: tox (>=3.0,<4.0); extra == "toml_tox"
Requires-Dist: urllib3 (>=1.25,<2.0)
Project-URL: Repository, https://github.com/kingsdigitallab/django-controlled-vocabulary
